Metadata-Version: 1.0
Name: issues
Version: 0.0.0
Summary: Issues
Home-page: https://github.com/nullelement/issues.git
Author: Thiago O. Dutra
Author-email: nullelement777@gmail.com
License: GPL v.3
Platform: UNKNOWN
